barrack/Medic.py
barrack/__init__.py
progrming0804-0.0.2.dist-info/LICENSE
progrming0804-0.0.2.dist-info/METADATA
progrming0804-0.0.2.dist-info/WHEEL
progrming0804-0.0.2.dist-info/top_level.txt
progrming0804-0.0.2.dist-info/RECORD
