Metadata-Version: 2.1
Name: progrming0804
Version: 0.0.2
Summary: KNUE_TEST
Home-page: https://github.com/dgmath8/programing0804
Author: Donggeun.Lee
Author-email: dgmath8@naver.com
License: UNKNOWN
Platform: UNKNOWN
Classifier: Programming Language :: Python :: 3
Classifier: License :: OSI Approved :: MIT License
Classifier: Operating System :: OS Independent
Requires-Python: >=3.6
